HDL_SRC/CORE/RegisterFile/reg_rw.v
/*
 * *****************************************************************
 * File: reg_rw.v
 * Project: xxx
 * File Created: 2018/11/25 06:54
 * Author: AAM ( aam.you@gmail.com )
 * *****
 * Last Modified: 2018/11/25 07:01
 * Modified By: AAM ( aam.you@gmail.com )
 * *****
 * Copyright 2018 - 2018  Project xxx
 * *****************************************************************
 * Description:
 *    R/W レジスタ
 * *****************************************************************
 * HISTORY:
 * Date      	By    	Comments
 * ----------	------	--------------------------------------------
 * 2018/11/25	AAM     First Version
 * *****************************************************************
 */

module reg_rw (
    clk, rst_n,
    wenble,
    datain, dataout
    );

    parameter XLEN = 32;
    parameter INIVAL = {XLEN{1'b0}};

    input   clk;                    // Clock
    input   rst_n;                  // Reset
    input   wenble;                 // データ書き込み
    input   [XLEN-1:0] datain;      // 入力データ
    output  [XLEN-1:0] dataout;     // 出力データ

    reg     [XLEN-1:0] data;        // 値を保持するデータレジスタ

    always @(posedge clk or negedge rst_n) begin
        if(~rst_n)
            data <= INIVAL;
        else if(wenble)
            data <= datain;
        else
            data <= data;
    end

    assign dataout = data;

endmodule // reg_rw

HDL_SIM/CORE/RegisterFile/reg_rw_tb.v
/*
 * *****************************************************************
 * File: reg_rw_tb.v
 * Project: xxx
 * File Created: 2018/11/25 06:43
 * Author: AAM ( aam.you@gmail.com )
 * *****
 * Last Modified: 2018/11/25 08:34
 * Modified By: aokim ( you@you.you )
 * *****
 * Copyright 2018 - 2018  Project xxx
 * *****************************************************************
 * Description:
 *    R/W レジスタ　テストベンチ
 * *****************************************************************
 * HISTORY:
 * Date      	By    	Comments
 * ----------	------	---------------------------------------------
 * 182018/11/25	AAM	    First Version
 * *****************************************************************
 */

module reg_rw_tb;

reg clk;
reg rst_n;
reg wenble;
reg [31:0] datain;
wire [31:0] dataout;

reg_rw test(
    clk, rst_n,
    wenble,
    datain, dataout
);

initial
    clk = 0;
always begin
    #5 clk = ~clk;
end

initial begin
    $dumpfile("reg_rw.vcd");
    $dumpvars(0,reg_rw_tb);
    $monitor("%t: en=%b  in=%h out=%h",$time,wenble,datain,dataout);

    rst_n = 0;
    wenble = 0;
    datain = 32'h00000000;
    @(posedge clk)
    @(posedge clk)
    rst_n = 1;

    @(posedge clk)
    datain = 32'haaaaaaaa;
    @(posedge clk)
    wenble = 1;
    @(posedge clk)
    wenble = 0;

    @(posedge clk)
    datain = 32'h55555555;
    @(posedge clk)
    wenble = 1;
    @(posedge clk)
    wenble = 0;

    @(posedge clk)
    datain = 32'h00000000;
    @(posedge clk)
    wenble = 1;
    @(posedge clk)
    wenble = 0;

    @(posedge clk)
    datain = 32'hffffffff;
    @(posedge clk)
    wenble = 1;
    @(posedge clk)
    wenble = 0;

    $finish;
end

endmodule

HDL_SIM/CORE/RegisterFile/reg_rw.vcd
$date
	Sun Nov 25 08:35:04 2018
$end
$version
	Icarus Verilog
$end
$timescale
	1s
$end
$scope module reg_rw_tb $end
$var wire 32 ! dataout [31:0] $end
$var reg 1 " clk $end
$var reg 32 # datain [31:0] $end
$var reg 1 $ rst_n $end
$var reg 1 % wenble $end
$scope module test $end
$var wire 1 " clk $end
$var wire 32 & datain [31:0] $end
$var wire 32 ' dataout [31:0] $end
$var wire 1 $ rst_n $end
$var wire 1 % wenble $end
$var reg 32 ( data [31:0] $end
$upscope $end
$upscope $end
$enddefinitions $end
#0
$dumpvars
b0 (
b0 '
b0 &
0%
0$
b0 #
0"
b0 !
$end
#5
1"
#10
0"
#15
1$
1"
#20
0"
#25
b10101010101010101010101010101010 #
b10101010101010101010101010101010 &
1"
#30
0"
#35
b10101010101010101010101010101010 !
b10101010101010101010101010101010 '
b10101010101010101010101010101010 (
1%
1"
#40
0"
#45
0%
1"
#50
0"
#55
b1010101010101010101010101010101 #
b1010101010101010101010101010101 &
1"
#60
0"
#65
b1010101010101010101010101010101 !
b1010101010101010101010101010101 '
b1010101010101010101010101010101 (
1%
1"
#70
0"
#75
0%
1"
#80
0"
#85
b0 #
b0 &
1"
#90
0"
#95
b0 !
b0 '
b0 (
1%
1"
#100
0"
#105
0%
1"
#110
0"
#115
b11111111111111111111111111111111 #
b11111111111111111111111111111111 &
1"
#120
0"
#125
b11111111111111111111111111111111 !
b11111111111111111111111111111111 '
b11111111111111111111111111111111 (
1%
1"
#130
0"
#135
0%
1"
